AUTHORS.rst
CONTRIBUTING.rst
HISTORY.rst
LICENSE
MANIFEST.in
README.md
setup.cfg
setup.py
data/PACKAGES
docs/Makefile
docs/authors.rst
docs/conf.py
docs/contributing.rst
docs/history.rst
docs/index.rst
docs/installation.rst
docs/make.bat
docs/readme.rst
docs/usage.rst
scienv/__init__.py
scienv/cli.py
scienv/scienv.py
scienv.egg-info/PKG-INFO
scienv.egg-info/SOURCES.txt
scienv.egg-info/dependency_links.txt
scienv.egg-info/entry_points.txt
scienv.egg-info/not-zip-safe
scienv.egg-info/requires.txt
scienv.egg-info/top_level.txt
tests/__init__.py
tests/test_scienv.py